LICENSE.txt
MANIFEST.in
README.md
pyproject.toml
setup.cfg
setup.py
ramdriver/__init__.py
ramdriver.egg-info/PKG-INFO
ramdriver.egg-info/SOURCES.txt
ramdriver.egg-info/dependency_links.txt
ramdriver.egg-info/requires.txt
ramdriver.egg-info/top_level.txt
ramdriver/cdp/README.md
ramdriver/cdp/__init__.py
ramdriver/cdp/accessibility.py
ramdriver/cdp/animation.py
ramdriver/cdp/audits.py
ramdriver/cdp/autofill.py
ramdriver/cdp/background_service.py
ramdriver/cdp/browser.py
ramdriver/cdp/cache_storage.py
ramdriver/cdp/cast.py
ramdriver/cdp/console.py
ramdriver/cdp/css.py
ramdriver/cdp/database.py
ramdriver/cdp/debugger.py
ramdriver/cdp/device_access.py
ramdriver/cdp/device_orientation.py
ramdriver/cdp/dom.py
ramdriver/cdp/dom_debugger.py
ramdriver/cdp/dom_snapshot.py
ramdriver/cdp/dom_storage.py
ramdriver/cdp/emulation.py
ramdriver/cdp/event_breakpoints.py
ramdriver/cdp/fed_cm.py
ramdriver/cdp/fetch.py
ramdriver/cdp/headless_experimental.py
ramdriver/cdp/heap_profiler.py
ramdriver/cdp/indexed_db.py
ramdriver/cdp/input_.py
ramdriver/cdp/inspector.py
ramdriver/cdp/io.py
ramdriver/cdp/layer_tree.py
ramdriver/cdp/log.py
ramdriver/cdp/media.py
ramdriver/cdp/memory.py
ramdriver/cdp/network.py
ramdriver/cdp/overlay.py
ramdriver/cdp/page.py
ramdriver/cdp/performance.py
ramdriver/cdp/performance_timeline.py
ramdriver/cdp/preload.py
ramdriver/cdp/profiler.py
ramdriver/cdp/py.typed
ramdriver/cdp/runtime.py
ramdriver/cdp/schema.py
ramdriver/cdp/security.py
ramdriver/cdp/service_worker.py
ramdriver/cdp/storage.py
ramdriver/cdp/system_info.py
ramdriver/cdp/target.py
ramdriver/cdp/tethering.py
ramdriver/cdp/tracing.py
ramdriver/cdp/util.py
ramdriver/cdp/web_audio.py
ramdriver/cdp/web_authn.py
ramdriver/core/_contradict.py
ramdriver/core/browser.py
ramdriver/core/config.py
ramdriver/core/connection.py
ramdriver/core/element.py
ramdriver/core/extra.py
ramdriver/core/tab.py
ramdriver/core/util.py